README.md
license.txt
setup.cfg
setup.py
EoN/__init__.py
EoN/analytic.py
EoN/auxiliary.py
EoN/class_based_visualization.py
EoN/legacy.py
EoN/simulation.py
EoN/simulation_investigation.py
EoN/simulation_investigation_old.py
EoN/simulation_new.py
EoN/visualization_save.py
EoN.egg-info/PKG-INFO
EoN.egg-info/SOURCES.txt
EoN.egg-info/dependency_links.txt
EoN.egg-info/requires.txt
EoN.egg-info/top_level.txt