Metadata-Version: 2.1
Name: EoN
Version: 1.2
Summary: Epidemics on Networks
Home-page: https://springer-math.github.io/Mathematics-of-Epidemics-on-Networks/
Download-URL: https://github.com/springer-math/Mathematics-of-Epidemics-on-Networks/archive/1.2.tar.gz
Author: Joel C. Miller, Istvan Z. Kiss, and Peter Simon
Author-email: joel.c.miller.research@gmail.com
Keywords: Epidemics on Networks,Epidemic Sonnet Works
License-File: license.txt
Requires-Dist: networkx>=2
Requires-Dist: numpy
Requires-Dist: scipy
Requires-Dist: matplotlib
